README.md
ignorer/LICENSE.md
ignorer/__init__.py
ignorer/gitignore/.git
ignorer/gitignore/.github/PULL_REQUEST_TEMPLATE.md
ignorer/gitignore/AL.gitignore
ignorer/gitignore/Actionscript.gitignore
ignorer/gitignore/Ada.gitignore
ignorer/gitignore/Agda.gitignore
ignorer/gitignore/Android.gitignore
ignorer/gitignore/AppEngine.gitignore
ignorer/gitignore/AppceleratorTitanium.gitignore
ignorer/gitignore/ArchLinuxPackages.gitignore
ignorer/gitignore/Autotools.gitignore
ignorer/gitignore/C++.gitignore
ignorer/gitignore/C.gitignore
ignorer/gitignore/CFWheels.gitignore
ignorer/gitignore/CMake.gitignore
ignorer/gitignore/CONTRIBUTING.md
ignorer/gitignore/CUDA.gitignore
ignorer/gitignore/CakePHP.gitignore
ignorer/gitignore/ChefCookbook.gitignore
ignorer/gitignore/CodeIgniter.gitignore
ignorer/gitignore/CommonLisp.gitignore
ignorer/gitignore/Composer.gitignore
ignorer/gitignore/Concrete5.gitignore
ignorer/gitignore/Coq.gitignore
ignorer/gitignore/CraftCMS.gitignore
ignorer/gitignore/D.gitignore
ignorer/gitignore/DM.gitignore
ignorer/gitignore/Dart.gitignore
ignorer/gitignore/Delphi.gitignore
ignorer/gitignore/Drupal.gitignore
ignorer/gitignore/EPiServer.gitignore
ignorer/gitignore/Eagle.gitignore
ignorer/gitignore/Elisp.gitignore
ignorer/gitignore/Elixir.gitignore
ignorer/gitignore/Elm.gitignore
ignorer/gitignore/Erlang.gitignore
ignorer/gitignore/ExpressionEngine.gitignore
ignorer/gitignore/ExtJs.gitignore
ignorer/gitignore/Fancy.gitignore
ignorer/gitignore/Finale.gitignore
ignorer/gitignore/FlaxEngine.gitignore
ignorer/gitignore/ForceDotCom.gitignore
ignorer/gitignore/FuelPHP.gitignore
ignorer/gitignore/GWT.gitignore
ignorer/gitignore/Gcov.gitignore
ignorer/gitignore/GitBook.gitignore
ignorer/gitignore/Global/AL.gitignore
ignorer/gitignore/Global/Anjuta.gitignore
ignorer/gitignore/Global/Ansible.gitignore
ignorer/gitignore/Global/Archives.gitignore
ignorer/gitignore/Global/Backup.gitignore
ignorer/gitignore/Global/Bazaar.gitignore
ignorer/gitignore/Global/BricxCC.gitignore
ignorer-1.0.3.dist-info/entry_points.txt
ignorer-1.0.3.dist-info/LICENSE.md
ignorer-1.0.3.dist-info/WHEEL
ignorer-1.0.3.dist-info/METADATA
ignorer-1.0.3.dist-info/RECORD
