Metadata-Version: 2.1
Name: ignorer
Version: 1.0.3
Summary: Generate .gitignore files from your command line
Home-page: https://github.com/celsiusnarhwal/ignorer
License: MIT
Keywords: gitignore,git,ignore,cli
Author: celsius narhwal
Author-email: hello@celsiusnarhwal.dev
Requires-Python: >=3.10,<4.0
Classifier: Development Status :: 5 - Production/Stable
Classifier: Environment :: Console
Classifier: Intended Audience :: Developers
Classifier: License :: OSI Approved :: MIT License
Classifier: Operating System :: OS Independent
Classifier: Programming Language :: Python :: 3
Classifier: Programming Language :: Python :: 3.10
Classifier: Programming Language :: Python :: 3.11
Classifier: Topic :: Software Development :: Code Generators
Classifier: Topic :: Utilities
Requires-Dist: click (>=8.1.3,<9.0.0)
Requires-Dist: inflect (>=6.0.2,<7.0.0)
Requires-Dist: inquirerpy (>=0.3.4,<0.4.0)
Requires-Dist: pyperclip (>=1.8.2,<2.0.0)
Project-URL: Repository, https://github.com/celsiusnarhwal/ignorer
